{  
   "mglo01j-l1Pt": {  
        "Initialize": {  
            "type": "TH1F",
            "nbins": 100,
            "xmin": 0,
            "xmax": 200
        },
        "Attributes": {  
            "SetLineColor": "ROOT.kSpring - 6",
            "SetLineWidth": 2,
            "SetMarkerSize" : 0,
            "GetXaxis().SetTitle": "Lepton 1 p_{T}",  
            "GetYaxis().SetTitle": "Events"  
        }
    },
   "mglo01j-l2Pt": {  
        "Initialize": {  
            "type": "TH1F",
            "nbins": 100,
            "xmin": 0,
            "xmax": 200
        },
        "Attributes": {  
            "SetLineColor": "ROOT.kSpring - 6",
            "SetLineWidth": 2,
            "SetMarkerSize" : 0,
            "GetXaxis().SetTitle": "Lepton 2 p_{T}",  
            "GetYaxis().SetTitle": "Events"  
        }
    },
   "mglo01j-l1Eta": {  
        "Initialize": {  
            "type": "TH1F",
            "nbins": 80,
            "xmin": -7,
            "xmax": 7
        },
        "Attributes": {  
            "SetLineColor": "ROOT.kSpring - 6",
            "SetLineWidth": 2,
            "SetMarkerSize" : 0,
            "GetXaxis().SetTitle": "lepton 1 #eta",  
            "GetYaxis().SetTitle": "Events"  
        }
    },
   "mglo01j-l2Eta": {  
        "Initialize": {  
            "type": "TH1F",
            "nbins": 80,
            "xmin": -7,
            "xmax": 7
        },
        "Attributes": {  
            "SetLineColor": "ROOT.kSpring - 6",
            "SetLineWidth": 2,
            "SetMarkerSize" : 0,
            "GetXaxis().SetTitle": "lepton 2 #eta",  
            "GetYaxis().SetTitle": "Events"  
        }
    },
   "mglo01j-j1Pt": {  
        "Initialize": {  
            "type": "TH1F",
            "nbins": 80,
            "xmin": 20,
            "xmax": 200
        },
        "Attributes": {  
            "SetLineColor": "ROOT.kSpring - 6",
            "SetLineWidth": 2,
            "SetMarkerSize" : 0,
            "GetXaxis().SetTitle": "Leading Jet p_{T}",  
            "GetYaxis().SetTitle": "Events"  
        }
    },
   "mglo01j-j1Eta": {  
        "Initialize": {  
            "type": "TH1F",
            "nbins": 80,
            "xmin": -7,
            "xmax": 7
        },
        "Attributes": {  
            "SetLineColor": "ROOT.kSpring - 6",
            "SetLineWidth": 2,
            "SetMarkerSize" : 0,
            "GetXaxis().SetTitle": "Leading Jet #eta",  
            "GetYaxis().SetTitle": "Events"  
        }
    },
   "mglo01j-j2Pt": {  
        "Initialize": {  
            "type": "TH1F",
            "nbins": 80,
            "xmin": 20,
            "xmax": 200
        },
        "Attributes": {  
            "SetLineColor": "ROOT.kSpring - 6",
            "SetLineWidth": 2,
            "SetMarkerSize" : 0,
            "GetXaxis().SetTitle": "Jet 2 p_{T}",  
            "GetYaxis().SetTitle": "Events"  
        }
    },
   "mglo01j-j2Eta": {  
        "Initialize": {  
            "type": "TH1F",
            "nbins": 80,
            "xmin": -7,
            "xmax": 7
        },
        "Attributes": {  
            "SetLineColor": "ROOT.kSpring - 6",
            "SetLineWidth": 2,
            "SetMarkerSize" : 0,
            "GetXaxis().SetTitle": "Jet 2 #eta",  
            "GetYaxis().SetTitle": "Events"  
        }
    },

   "mglo01j-nj": {  
        "Initialize": {  
            "type": "TH1F",
            "nbins": 7,
            "xmin": 0,
            "xmax": 7
        },
        "Attributes": {  
            "SetLineColor": "ROOT.kSpring - 6",
            "SetLineWidth": 2,
            "SetMarkerSize" : 0,
            "GetXaxis().SetTitle": "Number of p_{T} > 30 GeV GenJets",  
            "GetYaxis().SetTitle": "Events"  
        }
    },
    "mglo01j-zPt": {  
        "Initialize": {  
            "type": "TH1F",
            "nbins": 100,
            "xmin": 0,
            "xmax": 300
        },
        "Attributes": {  
            "SetLineColor": "ROOT.kSpring - 6",
            "SetLineWidth": 2,
            "SetMarkerSize" : 0,
            "GetXaxis().SetTitle": "p_{T}(Z) [GeV]",  
            "GetYaxis().SetTitle": "Events"  
        }
    },
  "mglo01j-zMass": {  
        "Initialize": {  
            "type": "TH1F",
            "nbins": 80,
            "xmin": 60,
            "xmax": 120
        },
        "Attributes": {  
            "SetLineColor": "ROOT.kSpring - 6",
            "SetLineWidth": 2,
            "SetMarkerSize" : 0,
            "GetXaxis().SetTitle": "M_{Z} [GeV]",  
            "GetYaxis().SetTitle": "Events",
            "GetYaxis().SetTitleOffset": 1.2  
        }
    },
   "Canvas": {  
        "Initialize": {  
            "type": "TCanvas",
            "ww": 800,
            "wh": 600
        },
        "Attributes": {
            "SetLeftMargin" : 1.2
        }
    }
}
